cli/__init__.py
cli/main.py
util/__init__.py
util/conversions.py
util/lookup_functions.py
valcli-0.0.8.dist-info/METADATA
valcli-0.0.8.dist-info/WHEEL
valcli-0.0.8.dist-info/entry_points.txt
valcli-0.0.8.dist-info/top_level.txt
valcli-0.0.8.dist-info/RECORD
