Metadata-Version: 2.1
Name: valcli
Version: 0.0.8
Summary: UNKNOWN
Home-page: UNKNOWN
License: UNKNOWN
Platform: UNKNOWN
Requires-Dist: click
Requires-Dist: requests
Requires-Dist: pyautogui
Requires-Dist: cryptography
